Workbook

Sheet README
A1: F1 Team Cost-Efficiency & Risk-Adjusted Performance Dashboard
B4: What this is
B5: A financial-efficiency model that cross-references each 2024 F1 constructor's championship points against
B6: team revenue and operating profit (Forbes estimates) to score risk-adjusted performance per $10M of revenue.
B8: How to use it
B9: 1. 'Raw Data' — the source table (points, revenue, operating profit). Blue cells are hardcoded inputs, sourced below.
B10: 2. 'Calculations' — all derived metrics, built entirely with formulas that recalc if you edit Raw Data.
B11: 3. 'Dashboard' — the 1-page visual summary + recommendation memo.
B12: 4. 'PowerBI_Source' — a flat, Table-formatted sheet designed to be imported straight into Power BI.
B14: Methodology
B15: Points per $10M Revenue = (2024 Points / Revenue) x 10 -> pure on-track return per dollar of top-line.
B16: Operating Margin = Operating Profit / Revenue -> financial health / downside risk indicator.
B17: Each metric is normalized 0-100 vs. the field (min-max scaling), then blended into a single
... B29: See the 'PowerBI_Guide' sheet for exact click-by-click steps to build the interactive report.

Sheet Raw Data
A1: Raw Data — 2024 F1 Constructor Points, Revenue & Operating Profit
A2: All financial figures are Forbes 2024 estimates (USD). Points are final 2024 FIA constructor standings. Blue = hardcoded input.
A4: Team | B4: 2024 Constructor Points | C4: 2024 Revenue ($M) | D4: 2024 Operating Profit ($M) | E4: Notes / Source
A5: McLaren | B5: 666 | C5: 614 | D5: 61 | E5: Constructors' Champion 2024. Source: Forbes F1 Valuations 2025.
A6: Ferrari | B6: 652 | C6: 670 | D6: 80 | E6: Runner-up, 14 pts behind. Source: Forbes F1 Valuations 2025.
A7: Red Bull Racing | B7: 589 | C7: 618 | D7: 26 | E7: 3rd in standings. Source: Forbes F1 Valuations 2025.
A8: Mercedes | B8: 468 | C8: 799 | D8: 202 | E8: 4th in standings; highest revenue on grid. Source: Forbes F1 Valuations 2025.
A9: Aston Martin | B9: 94 | C9: 353 | D9: -18 | E9: 5th in standings; operating loss. Source: Forbes F1 Valuations 2025.
A10: Alpine | B10: 65 | C10: 300 | D10: -13 | E10: 6th in standings; operating loss. Source: Forbes F1 Valuations 2025.
A11: Haas | B11: 58 | C11: 150 | D11: 9 | E11: 7th in standings; smallest revenue base. Source: Forbes F1 Valuations 2025.
A12: Racing Bulls (RB) | B12: 46 | C12: 318 | D12: 5 | E12: 8th in standings (raced as VCARB/RB in 2024). Source: Forbes F1 Valuations 2025.
A13: Williams | B13: 17 | C13: 245 | D13: -36 | E13: 9th in standings; operating loss. Source: Forbes F1 Valuations 2025.
A14: Sauber | B14: 4 | C14: 240 | D14: -25 | E14: 10th in standings (raced as Kick Sauber in 2024). Source: Forbes F1 Valuations 2025.
A15: Field Total / Avg | B15: =SUM(B5:B14) -> 2659 | C15: =AVERAGE(C5:C14) -> 430.7 | D15: =AVERAGE(D5:D14) -> 29.1

Sheet Calculations
A1: Risk-Adjusted Performance Calculations
A3: Efficiency Weight | B3: 0.7 | C3: <- edit to re-weight the blend (financial stability weight auto-adjusts to 1 - this)
A4: Financial Stability Weight | B4: =1-B3 -> 0.3
A6: Team | B6: Points | C6: Revenue ($M) | D6: Op. Profit ($M) | E6: Points per $10M Rev | F6: Operating Margin | G6: Efficiency Score (0-100) | H6: Financial Stability Score (0-100) | I6: Risk-Adjusted Score | J6: Rank
A7: ='Raw Data'!A5 -> McLaren | B7: ='Raw Data'!B5 -> 666 | C7: ='Raw Data'!C5 -> 614 | D7: ='Raw Data'!D5 -> 61 | E7: =IFERROR(B7/C7*10,0) -> 10.846906 | F7: =IFERROR(D7/C7,0) -> 0.099348534 | G7: =IFERROR((E7-MIN($E$7:$E$16))/(MAX($E$7:$E$16)-MIN($E$7:$E$16))*100,0) -> 100 | H7: =IFERROR((F7-MIN($F$7:$F$16))/(MAX($F$7:$F$16)-MIN($F$7:$F$16))*100,0) -> 61.609595 | I7: =G7*$B$3+H7*$B$4 -> 88.482878 | J7: =RANK(I7,$I$7:$I$16,0) -> 1
A8: ='Raw Data'!A6 -> Ferrari | B8: ='Raw Data'!B6 -> 652 | C8: ='Raw Data'!C6 -> 670 | D8: ='Raw Data'!D6 -> 80 | E8: =IFERROR(B8/C8*10,0) -> 9.7313433 | F8: =IFERROR(D8/C8,0) -> 0.11940299 | G8: =IFERROR((E8-MIN($E$7:$E$16))/(MAX($E$7:$E$16)-MIN($E$7:$E$16))*100,0) -> 89.554894 | H8: =IFERROR((F8-MIN($F$7:$F$16))/(MAX($F$7:$F$16)-MIN($F$7:$F$16))*100,0) -> 66.626283 | I8: =G8*$B$3+H8*$B$4 -> 82.676311 | J8: =RANK(I8,$I$7:$I$16,0) -> 2
A9: ='Raw Data'!A7 -> Red Bull Racing | B9: ='Raw Data'!B7 -> 589 | C9: ='Raw Data'!C7 -> 618 | D9: ='Raw Data'!D7 -> 26 | E9: =IFERROR(B9/C9*10,0) -> 9.5307443 | F9: =IFERROR(D9/C9,0) -> 0.042071197 | G9: =IFERROR((E9-MIN($E$7:$E$16))/(MAX($E$7:$E$16)-MIN($E$7:$E$16))*100,0) -> 87.676669 | H9: =IFERROR((F9-MIN($F$7:$F$16))/(MAX($F$7:$F$16)-MIN($F$7:$F$16))*100,0) -> 47.281477 | I9: =G9*$B$3+H9*$B$4 -> 75.558111 | J9: =RANK(I9,$I$7:$I$16,0) -> 3
A10: ='Raw Data'!A8 -> Mercedes | B10: ='Raw Data'!B8 -> 468 | C10: ='Raw Data'!C8 -> 799 | D10: ='Raw Data'!D8 -> 202 | E10: =IFERROR(B10/C10*10,0) -> 5.8573217 | F10: =IFERROR(D10/C10,0) -> 0.25281602 | G10: =IFERROR((E10-MIN($E$7:$E$16))/(MAX($E$7:$E$16)-MIN($E$7:$E$16))*100,0) -> 53.282095 | H10: =IFERROR((F10-MIN($F$7:$F$16))/(MAX($F$7:$F$16)-MIN($F$7:$F$16))*100,0) -> 100 | I10: =G10*$B$3+H10*$B$4 -> 67.297466 | J10: =RANK(I10,$I$7:$I$16,0) -> 4
A11: ='Raw Data'!A9 -> Aston Martin | B11: ='Raw Data'!B9 -> 94 | C11: ='Raw Data'!C9 -> 353 | D11: ='Raw Data'!D9 -> -18 | E11: =IFERROR(B11/C11*10,0) -> 2.6628895 | F11: =IFERROR(D11/C11,0) -> -0.050991501 | G11: =IFERROR((E11-MIN($E$7:$E$16))/(MAX($E$7:$E$16)-MIN($E$7:$E$16))*100,0) -> 23.37235 | H11: =IFERROR((F11-MIN($F$7:$F$16))/(MAX($F$7:$F$16)-MIN($F$7:$F$16))*100,0) -> 24.001532 | I11: =G11*$B$3+H11*$B$4 -> 23.561105 | J11: =RANK(I11,$I$7:$I$16,0) -> 6
A12: ='Raw Data'!A10 -> Alpine | B12: ='Raw Data'!B10 -> 65 | C12: ='Raw Data'!C10 -> 300 | D12: ='Raw Data'!D10 -> -13 | E12: =IFERROR(B12/C12*10,0) -> 2.1666667 | F12: =IFERROR(D12/C12,0) -> -0.043333333 | G12: =IFERROR((E12-MIN($E$7:$E$16))/(MAX($E$7:$E$16)-MIN($E$7:$E$16))*100,0) -> 18.726173 | H12: =IFERROR((F12-MIN($F$7:$F$16))/(MAX($F$7:$F$16)-MIN($F$7:$F$16))*100,0) -> 25.917248 | I12: =G12*$B$3+H12*$B$4 -> 20.883495 | J12: =RANK(I12,$I$7:$I$16,0) -> 7
A13: ='Raw Data'!A11 -> Haas | B13: ='Raw Data'!B11 -> 58 | C13: ='Raw Data'!C11 -> 150 | D13: ='Raw Data'!D11 -> 9 | E13: =IFERROR(B13/C13*10,0) -> 3.8666667 | F13: =IFERROR(D13/C13,0) -> 0.06 | G13: =IFERROR((E13-MIN($E$7:$E$16))/(MAX($E$7:$E$16)-MIN($E$7:$E$16))*100,0) -> 34.64342 | H13: =IFERROR((F13-MIN($F$7:$F$16))/(MAX($F$7:$F$16)-MIN($F$7:$F$16))*100,0) -> 51.766427 | I13: =G13*$B$3+H13*$B$4 -> 39.780322 | J13: =RANK(I13,$I$7:$I$16,0) -> 5
A14: ='Raw Data'!A12 -> Racing Bulls (RB) | B14: ='Raw Data'!B12 -> 46 | C14: ='Raw Data'!C12 -> 318 | D14: ='Raw Data'!D12 -> 5 | E14: =IFERROR(B14/C14*10,0) -> 1.4465409 | F14: =IFERROR(D14/C14,0) -> 0.01572327 | G14: =IFERROR((E14-MIN($E$7:$E$16))/(MAX($E$7:$E$16)-MIN($E$7:$E$16))*100,0) -> 11.983573 | H14: =IFERROR((F14-MIN($F$7:$F$16))/(MAX($F$7:$F$16)-MIN($F$7:$F$16))*100,0) -> 40.690455 | I14: =G14*$B$3+H14*$B$4 -> 20.595638 | J14: =RANK(I14,$I$7:$I$16,0) -> 8
A15: ='Raw Data'!A13 -> Williams | B15: ='Raw Data'!B13 -> 17 | C15: ='Raw Data'!C13 -> 245 | D15: ='Raw Data'!D13 -> -36 | E15: =IFERROR(B15/C15*10,0) -> 0.69387755 | F15: =IFERROR(D15/C15,0) -> -0.14693878 | G15: =IFERROR((E15-MIN($E$7:$E$16))/(MAX($E$7:$E$16)-MIN($E$7:$E$16))*100,0) -> 4.9363211 | H15: =IFERROR((F15-MIN($F$7:$F$16))/(MAX($F$7:$F$16)-MIN($F$7:$F$16))*100,0) -> 0 | I15: =G15*$B$3+H15*$B$4 -> 3.4554248 | J15: =RANK(I15,$I$7:$I$16,0) -> 9
A16: ='Raw Data'!A14 -> Sauber | B16: ='Raw Data'!B14 -> 4 | C16: ='Raw Data'!C14 -> 240 | D16: ='Raw Data'!D14 -> -25 | E16: =IFERROR(B16/C16*10,0) -> 0.16666667 | F16: =IFERROR(D16/C16,0) -> -0.10416667 | G16: =IFERROR((E16-MIN($E$7:$E$16))/(MAX($E$7:$E$16)-MIN($E$7:$E$16))*100,0) -> 0 | H16: =IFERROR((F16-MIN($F$7:$F$16))/(MAX($F$7:$F$16)-MIN($F$7:$F$16))*100,0) -> 10.699586 | I16: =G16*$B$3+H16*$B$4 -> 3.2098759 | J16: =RANK(I16,$I$7:$I$16,0) -> 10
A18: Efficiency Score and Financial Stability Score are min-max normalized (0 = weakest in field, 100 = strongest in field).
A19: Risk-Adjusted Score = Efficiency Score x Efficiency Weight + Financial Stability Score x Financial Stability Weight.

Sheet Dashboard
A1: F1 Team Cost-Efficiency & Risk-Adjusted Performance — 2024
A4: Rank | B4: Team | C4: Points | D4: Revenue ($M) | E4: Op. Profit ($M) | F4: Pts / $10M Rev | G4: Op. Margin | H4: Risk-Adjusted Score
A5: 1 | B5: =INDEX(Calculations!$A$7:$A$16,MATCH(A5,Calculations!$J$7:$J$16,0)) -> McLaren | C5: =INDEX(Calculations!$B$7:$B$16,MATCH($A5,Calculations!$J$7:$J$16,0)) -> 666 | D5: =INDEX(Calculations!$C$7:$C$16,MATCH($A5,Calculations!$J$7:$J$16,0)) -> 614 | E5: =INDEX(Calculations!$D$7:$D$16,MATCH($A5,Calculations!$J$7:$J$16,0)) -> 61 | F5: =INDEX(Calculations!$E$7:$E$16,MATCH($A5,Calculations!$J$7:$J$16,0)) -> 10.846906 | G5: =INDEX(Calculations!$F$7:$F$16,MATCH($A5,Calculations!$J$7:$J$16,0)) -> 0.099348534 | H5: =INDEX(Calculations!$I$7:$I$16,MATCH($A5,Calculations!$J$7:$J$16,0)) -> 88.482878
A6: 2 | B6: =INDEX(Calculations!$A$7:$A$16,MATCH(A6,Calculations!$J$7:$J$16,0)) -> Ferrari | C6: =INDEX(Calculations!$B$7:$B$16,MATCH($A6,Calculations!$J$7:$J$16,0)) -> 652 | D6: =INDEX(Calculations!$C$7:$C$16,MATCH($A6,Calculations!$J$7:$J$16,0)) -> 670 | E6: =INDEX(Calculations!$D$7:$D$16,MATCH($A6,Calculations!$J$7:$J$16,0)) -> 80 | F6: =INDEX(Calculations!$E$7:$E$16,MATCH($A6,Calculations!$J$7:$J$16,0)) -> 9.7313433 | G6: =INDEX(Calculations!$F$7:$F$16,MATCH($A6,Calculations!$J$7:$J$16,0)) -> 0.11940299 | H6: =INDEX(Calculations!$I$7:$I$16,MATCH($A6,Calculations!$J$7:$J$16,0)) -> 82.676311
A7: 3 | B7: =INDEX(Calculations!$A$7:$A$16,MATCH(A7,Calculations!$J$7:$J$16,0)) -> Red Bull Racing | C7: =INDEX(Calculations!$B$7:$B$16,MATCH($A7,Calculations!$J$7:$J$16,0)) -> 589 | D7: =INDEX(Calculations!$C$7:$C$16,MATCH($A7,Calculations!$J$7:$J$16,0)) -> 618 | E7: =INDEX(Calculations!$D$7:$D$16,MATCH($A7,Calculations!$J$7:$J$16,0)) -> 26 | F7: =INDEX(Calculations!$E$7:$E$16,MATCH($A7,Calculations!$J$7:$J$16,0)) -> 9.5307443 | G7: =INDEX(Calculations!$F$7:$F$16,MATCH($A7,Calculations!$J$7:$J$16,0)) -> 0.042071197 | H7: =INDEX(Calculations!$I$7:$I$16,MATCH($A7,Calculations!$J$7:$J$16,0)) -> 75.558111
A8: 4 | B8: =INDEX(Calculations!$A$7:$A$16,MATCH(A8,Calculations!$J$7:$J$16,0)) -> Mercedes | C8: =INDEX(Calculations!$B$7:$B$16,MATCH($A8,Calculations!$J$7:$J$16,0)) -> 468 | D8: =INDEX(Calculations!$C$7:$C$16,MATCH($A8,Calculations!$J$7:$J$16,0)) -> 799 | E8: =INDEX(Calculations!$D$7:$D$16,MATCH($A8,Calculations!$J$7:$J$16,0)) -> 202 | F8: =INDEX(Calculations!$E$7:$E$16,MATCH($A8,Calculations!$J$7:$J$16,0)) -> 5.8573217 | G8: =INDEX(Calculations!$F$7:$F$16,MATCH($A8,Calculations!$J$7:$J$16,0)) -> 0.25281602 | H8: =INDEX(Calculations!$I$7:$I$16,MATCH($A8,Calculations!$J$7:$J$16,0)) -> 67.297466
A9: 5 | B9: =INDEX(Calculations!$A$7:$A$16,MATCH(A9,Calculations!$J$7:$J$16,0)) -> Haas | C9: =INDEX(Calculations!$B$7:$B$16,MATCH($A9,Calculations!$J$7:$J$16,0)) -> 58 | D9: =INDEX(Calculations!$C$7:$C$16,MATCH($A9,Calculations!$J$7:$J$16,0)) -> 150 | E9: =INDEX(Calculations!$D$7:$D$16,MATCH($A9,Calculations!$J$7:$J$16,0)) -> 9 | F9: =INDEX(Calculations!$E$7:$E$16,MATCH($A9,Calculations!$J$7:$J$16,0)) -> 3.8666667 | G9: =INDEX(Calculations!$F$7:$F$16,MATCH($A9,Calculations!$J$7:$J$16,0)) -> 0.06 | H9: =INDEX(Calculations!$I$7:$I$16,MATCH($A9,Calculations!$J$7:$J$16,0)) -> 39.780322
A10: 6 | B10: =INDEX(Calculations!$A$7:$A$16,MATCH(A10,Calculations!$J$7:$J$16,0)) -> Aston Martin | C10: =INDEX(Calculations!$B$7:$B$16,MATCH($A10,Calculations!$J$7:$J$16,0)) -> 94 | D10: =INDEX(Calculations!$C$7:$C$16,MATCH($A10,Calculations!$J$7:$J$16,0)) -> 353 | E10: =INDEX(Calculations!$D$7:$D$16,MATCH($A10,Calculations!$J$7:$J$16,0)) -> -18 | F10: =INDEX(Calculations!$E$7:$E$16,MATCH($A10,Calculations!$J$7:$J$16,0)) -> 2.6628895 | G10: =INDEX(Calculations!$F$7:$F$16,MATCH($A10,Calculations!$J$7:$J$16,0)) -> -0.050991501 | H10: =INDEX(Calculations!$I$7:$I$16,MATCH($A10,Calculations!$J$7:$J$16,0)) -> 23.561105
A11: 7 | B11: =INDEX(Calculations!$A$7:$A$16,MATCH(A11,Calculations!$J$7:$J$16,0)) -> Alpine | C11: =INDEX(Calculations!$B$7:$B$16,MATCH($A11,Calculations!$J$7:$J$16,0)) -> 65 | D11: =INDEX(Calculations!$C$7:$C$16,MATCH($A11,Calculations!$J$7:$J$16,0)) -> 300 | E11: =INDEX(Calculations!$D$7:$D$16,MATCH($A11,Calculations!$J$7:$J$16,0)) -> -13 | F11: =INDEX(Calculations!$E$7:$E$16,MATCH($A11,Calculations!$J$7:$J$16,0)) -> 2.1666667 | G11: =INDEX(Calculations!$F$7:$F$16,MATCH($A11,Calculations!$J$7:$J$16,0)) -> -0.043333333 | H11: =INDEX(Calculations!$I$7:$I$16,MATCH($A11,Calculations!$J$7:$J$16,0)) -> 20.883495
A12: 8 | B12: =INDEX(Calculations!$A$7:$A$16,MATCH(A12,Calculations!$J$7:$J$16,0)) -> Racing Bulls (RB) | C12: =INDEX(Calculations!$B$7:$B$16,MATCH($A12,Calculations!$J$7:$J$16,0)) -> 46 | D12: =INDEX(Calculations!$C$7:$C$16,MATCH($A12,Calculations!$J$7:$J$16,0)) -> 318 | E12: =INDEX(Calculations!$D$7:$D$16,MATCH($A12,Calculations!$J$7:$J$16,0)) -> 5 | F12: =INDEX(Calculations!$E$7:$E$16,MATCH($A12,Calculations!$J$7:$J$16,0)) -> 1.4465409 | G12: =INDEX(Calculations!$F$7:$F$16,MATCH($A12,Calculations!$J$7:$J$16,0)) -> 0.01572327 | H12: =INDEX(Calculations!$I$7:$I$16,MATCH($A12,Calculations!$J$7:$J$16,0)) -> 20.595638
A13: 9 | B13: =INDEX(Calculations!$A$7:$A$16,MATCH(A13,Calculations!$J$7:$J$16,0)) -> Williams | C13: =INDEX(Calculations!$B$7:$B$16,MATCH($A13,Calculations!$J$7:$J$16,0)) -> 17 | D13: =INDEX(Calculations!$C$7:$C$16,MATCH($A13,Calculations!$J$7:$J$16,0)) -> 245 | E13: =INDEX(Calculations!$D$7:$D$16,MATCH($A13,Calculations!$J$7:$J$16,0)) -> -36 | F13: =INDEX(Calculations!$E$7:$E$16,MATCH($A13,Calculations!$J$7:$J$16,0)) -> 0.69387755 | G13: =INDEX(Calculations!$F$7:$F$16,MATCH($A13,Calculations!$J$7:$J$16,0)) -> -0.14693878 | H13: =INDEX(Calculations!$I$7:$I$16,MATCH($A13,Calculations!$J$7:$J$16,0)) -> 3.4554248
A14: 10 | B14: =INDEX(Calculations!$A$7:$A$16,MATCH(A14,Calculations!$J$7:$J$16,0)) -> Sauber | C14: =INDEX(Calculations!$B$7:$B$16,MATCH($A14,Calculations!$J$7:$J$16,0)) -> 4 | D14: =INDEX(Calculations!$C$7:$C$16,MATCH($A14,Calculations!$J$7:$J$16,0)) -> 240 | E14: =INDEX(Calculations!$D$7:$D$16,MATCH($A14,Calculations!$J$7:$J$16,0)) -> -25 | F14: =INDEX(Calculations!$E$7:$E$16,MATCH($A14,Calculations!$J$7:$J$16,0)) -> 0.16666667 | G14: =INDEX(Calculations!$F$7:$F$16,MATCH($A14,Calculations!$J$7:$J$16,0)) -> -0.10416667 | H14: =INDEX(Calculations!$I$7:$I$16,MATCH($A14,Calculations!$J$7:$J$16,0)) -> 3.2098759
A53: 1-Page Recommendation Memo
A54: Headline finding: McLaren and Ferrari lead the grid on risk-adjusted, revenue-normalized performance — not just on
A55: raw championship points. Both convert revenue into on-track results efficiently while running healthy operating margins,
A56: which is what the composite score is designed to reward over teams that simply outspend the field.
A58: Efficiency vs. scale: Mercedes has the largest revenue base ($799M) and strongest operating profit ($202M) but finished
A59: 4th in points — its per-$10M efficiency score is pulled down by that scale, even though it is the field's most
A60: financially stable team. This is exactly the tradeoff the model is built to surface: bigger budgets don't automatically
A61: mean better return per dollar.
A63: Risk flags: Aston Martin, Alpine, Williams and Sauber posted 2024 operating losses. Their financial-stability scores
A64: drag down their composite ranking even where on-track points are respectable relative to spend, which is the intended
A65: 'risk-adjustment' — a team burning cash to compete is a riskier proposition for investors/sponsors than one that isn't.
A67: Recommendation: For a sponsor or investor evaluating value-for-money, McLaren and Ferrari currently offer the best
... A73: underlying dollar figures as directionally accurate rather than exact.

Sheet PowerBI_Source
A1: Power BI Source Table — import this sheet's table into Power BI Desktop
A3: Team | B3: Points | C3: Revenue_USD_M | D3: OperatingProfit_USD_M | E3: PointsPer10MRev | F3: OperatingMargin | G3: EfficiencyScore | H3: FinancialStabilityScore | I3: RiskAdjustedScore | J3: Rank
A4: =Calculations!A7 -> McLaren | B4: =Calculations!B7 -> 666 | C4: =Calculations!C7 -> 614 | D4: =Calculations!D7 -> 61 | E4: =Calculations!E7 -> 10.846906 | F4: =Calculations!F7 -> 0.099348534 | G4: =Calculations!G7 -> 100 | H4: =Calculations!H7 -> 61.609595 | ... J4: =Calculations!J7 -> 1
A5: =Calculations!A8 -> Ferrari | B5: =Calculations!B8 -> 652 | C5: =Calculations!C8 -> 670 | D5: =Calculations!D8 -> 80 | E5: =Calculations!E8 -> 9.7313433 | F5: =Calculations!F8 -> 0.11940299 | G5: =Calculations!G8 -> 89.554894 | H5: =Calculations!H8 -> 66.626283 | ... J5: =Calculations!J8 -> 2
A6: =Calculations!A9 -> Red Bull Racing | B6: =Calculations!B9 -> 589 | C6: =Calculations!C9 -> 618 | D6: =Calculations!D9 -> 26 | E6: =Calculations!E9 -> 9.5307443 | F6: =Calculations!F9 -> 0.042071197 | G6: =Calculations!G9 -> 87.676669 | H6: =Calculations!H9 -> 47.281477 | ... J6: =Calculations!J9 -> 3
A7: =Calculations!A10 -> Mercedes | B7: =Calculations!B10 -> 468 | C7: =Calculations!C10 -> 799 | D7: =Calculations!D10 -> 202 | E7: =Calculations!E10 -> 5.8573217 | F7: =Calculations!F10 -> 0.25281602 | G7: =Calculations!G10 -> 53.282095 | H7: =Calculations!H10 -> 100 | ... J7: =Calculations!J10 -> 4
A8: =Calculations!A11 -> Aston Martin | B8: =Calculations!B11 -> 94 | C8: =Calculations!C11 -> 353 | D8: =Calculations!D11 -> -18 | E8: =Calculations!E11 -> 2.6628895 | F8: =Calculations!F11 -> -0.050991501 | G8: =Calculations!G11 -> 23.37235 | H8: =Calculations!H11 -> 24.001532 | ... J8: =Calculations!J11 -> 6
A9: =Calculations!A12 -> Alpine | B9: =Calculations!B12 -> 65 | C9: =Calculations!C12 -> 300 | D9: =Calculations!D12 -> -13 | E9: =Calculations!E12 -> 2.1666667 | F9: =Calculations!F12 -> -0.043333333 | G9: =Calculations!G12 -> 18.726173 | H9: =Calculations!H12 -> 25.917248 | ... J9: =Calculations!J12 -> 7
A10: =Calculations!A13 -> Haas | B10: =Calculations!B13 -> 58 | C10: =Calculations!C13 -> 150 | D10: =Calculations!D13 -> 9 | E10: =Calculations!E13 -> 3.8666667 | F10: =Calculations!F13 -> 0.06 | G10: =Calculations!G13 -> 34.64342 | H10: =Calculations!H13 -> 51.766427 | ... J10: =Calculations!J13 -> 5
A11: =Calculations!A14 -> Racing Bulls (RB) | B11: =Calculations!B14 -> 46 | C11: =Calculations!C14 -> 318 | D11: =Calculations!D14 -> 5 | E11: =Calculations!E14 -> 1.4465409 | F11: =Calculations!F14 -> 0.01572327 | G11: =Calculations!G14 -> 11.983573 | H11: =Calculations!H14 -> 40.690455 | ... J11: =Calculations!J14 -> 8
A12: =Calculations!A15 -> Williams | B12: =Calculations!B15 -> 17 | C12: =Calculations!C15 -> 245 | D12: =Calculations!D15 -> -36 | E12: =Calculations!E15 -> 0.69387755 | F12: =Calculations!F15 -> -0.14693878 | G12: =Calculations!G15 -> 4.9363211 | H12: =Calculations!H15 -> 0 | ... J12: =Calculations!J15 -> 9
A13: =Calculations!A16 -> Sauber | B13: =Calculations!B16 -> 4 | C13: =Calculations!C16 -> 240 | D13: =Calculations!D16 -> -25 | E13: =Calculations!E16 -> 0.16666667 | F13: =Calculations!F16 -> -0.10416667 | G13: =Calculations!G16 -> 0 | H13: =Calculations!H16 -> 10.699586 | ... J13: =Calculations!J16 -> 10
A15: Tip: In Power BI Desktop, Get Data -> Excel Workbook -> select this file -> check the 'PowerBISource' table (not the whole sheet).

Sheet PowerBI_Guide
A1: Building This in Power BI — Step by Step
B4: Note
B5: Power BI Desktop is a Windows/Mac desktop app, so it can't be generated inside this chat — but this workbook
B6: is built so you can import it directly and have a working report in about 10 minutes. Steps below.
B8: Step 1 — Get the data
B9: Open Power BI Desktop -> Home -> Get Data -> Excel Workbook -> select this .xlsx file.
B10: In the Navigator window, tick the 'PowerBISource' table (it's the flat, formula-driven table on the
B11: 'PowerBI_Source' tab) -> click Transform Data (recommended) or Load.
B13: Step 2 — Check data types
B14: In Power Query Editor, confirm: Team = Text; Points, Revenue_USD_M, OperatingProfit_USD_M,
B15: PointsPer10MRev = Decimal Number; OperatingMargin = Percentage; the three Score columns = Decimal Number;
B16: Rank = Whole Number. Click Close & Apply.
B18: Step 3 — Build the visuals
... B48: RETURN EffScore * 0.7 + MarScore * 0.3
